LICENSE
README.md
setup.py
cloudmersive_documentai_api_client/__init__.py
cloudmersive_documentai_api_client/api_client.py
cloudmersive_documentai_api_client/configuration.py
cloudmersive_documentai_api_client/rest.py
cloudmersive_documentai_api_client.egg-info/PKG-INFO
cloudmersive_documentai_api_client.egg-info/SOURCES.txt
cloudmersive_documentai_api_client.egg-info/dependency_links.txt
cloudmersive_documentai_api_client.egg-info/requires.txt
cloudmersive_documentai_api_client.egg-info/top_level.txt
cloudmersive_documentai_api_client/api/__init__.py
cloudmersive_documentai_api_client/api/analyze_api.py
cloudmersive_documentai_api_client/api/extract_api.py
cloudmersive_documentai_api_client/api/run_batch_job_api.py
cloudmersive_documentai_api_client/models/__init__.py
cloudmersive_documentai_api_client/models/advanced_extract_classification_request.py
cloudmersive_documentai_api_client/models/advanced_extract_fields_request.py
cloudmersive_documentai_api_client/models/document_advanced_classification_result.py
cloudmersive_documentai_api_client/models/document_categories.py
cloudmersive_documentai_api_client/models/document_classification_result.py
cloudmersive_documentai_api_client/models/document_policy_request.py
cloudmersive_documentai_api_client/models/document_policy_result.py
cloudmersive_documentai_api_client/models/extract_barcodes_ai_response.py
cloudmersive_documentai_api_client/models/extract_document_batch_job_result.py
cloudmersive_documentai_api_client/models/extract_document_job_status_result.py
cloudmersive_documentai_api_client/models/extract_fields_advanced_response.py
cloudmersive_documentai_api_client/models/extract_fields_and_tables_response.py
cloudmersive_documentai_api_client/models/extract_fields_response.py
cloudmersive_documentai_api_client/models/extract_tables_response.py
cloudmersive_documentai_api_client/models/extract_text_response.py
cloudmersive_documentai_api_client/models/extracted_barcode_item.py
cloudmersive_documentai_api_client/models/extracted_text_page.py
cloudmersive_documentai_api_client/models/field_advanced_value.py
cloudmersive_documentai_api_client/models/field_to_extract.py
cloudmersive_documentai_api_client/models/field_value.py
cloudmersive_documentai_api_client/models/policy_rule.py
