Metadata-Version: 2.4
Name: cloudmersive_documentai_api_client
Version: 3.0.5
Summary: Document AI API
Home-page: https://cloudmersive.com/document-ai-api
Author-email: 
Keywords: Swagger,Document AI API
License-File: LICENSE
Requires-Dist: certifi>=2017.4.17
Requires-Dist: python-dateutil>=2.1
Requires-Dist: six>=1.10
Requires-Dist: urllib3>=1.23
Dynamic: description
Dynamic: description-content-type
Dynamic: home-page
Dynamic: keywords
Dynamic: license-file
Dynamic: requires-dist
Dynamic: summary
